xtea/__init__.py
xtea/counter.py
xtea-0.7.1.dist-info/METADATA
xtea-0.7.1.dist-info/WHEEL
xtea-0.7.1.dist-info/top_level.txt
xtea-0.7.1.dist-info/RECORD
